clutch/__init__.py
clutch/templates/clutch/clutch.html
clutch/templatetags/__init__.py
clutch/templatetags/clutch_tags.py
django_clutch_widget-0.0.2.dist-info/LICENSE
django_clutch_widget-0.0.2.dist-info/METADATA
django_clutch_widget-0.0.2.dist-info/WHEEL
django_clutch_widget-0.0.2.dist-info/top_level.txt
django_clutch_widget-0.0.2.dist-info/RECORD
